app.py
twitchsync/StreamsyncConfig.py
twitchsync/TwitchClient.py
twitchsync/TwitchSync.py
twitchsync/__init__.py
twitchsync/__main__.py
twitchsync-2.1.5.dist-info/licenses/LICENSE
twitchsync-2.1.5.dist-info/METADATA
twitchsync-2.1.5.dist-info/WHEEL
twitchsync-2.1.5.dist-info/entry_points.txt
twitchsync-2.1.5.dist-info/top_level.txt
twitchsync-2.1.5.dist-info/RECORD
