Metadata-Version: 2.4
Name: twitchsync
Version: 2.1.5
Summary: Gets matching timestamps for multiple streamers from a single twitch clip or timestamp.
Author-email: Patrick Seute <patrick.seute@gmail.com>
License-Expression: MIT
Project-URL: Homepage, https://github.com/SuperRonJon/TwitchSync
Project-URL: Issues, https://github.com/SuperRonJon/TwitchSync/issues
Classifier: Programming Language :: Python :: 3
Classifier: Operating System :: OS Independent
Requires-Python: >=3.9
License-File: LICENSE
Requires-Dist: requests
Requires-Dist: python-dateutil
Requires-Dist: isodate
Dynamic: license-file
